common_hht/__init__.py
common_hht-0.0.0.dist-info/METADATA
common_hht-0.0.0.dist-info/WHEEL
common_hht-0.0.0.dist-info/RECORD
