Metadata-Version: 2.4
Name: common-hht
Version: 0.0.0
Summary: Place holder package, not meant to be used
Author-email: Bagard Hoel <hoel.bagard@gmail.com>
Requires-Python: >=3.7
